codenerix_reviews/__init__.py
codenerix_reviews/admin.py
codenerix_reviews/apps.py
codenerix_reviews/forms.py
codenerix_reviews/models.py
codenerix_reviews/tests.py
codenerix_reviews/urls.py
codenerix_reviews/views.py
codenerix_reviews/migrations/0001_initial.py
codenerix_reviews/migrations/0002_alter_reviews_validate.py
codenerix_reviews/migrations/__init__.py
codenerix_reviews/migrations/__pycache__/0001_initial.cpython-35.pyc
codenerix_reviews/migrations/__pycache__/0001_initial.cpython-39.pyc
codenerix_reviews/migrations/__pycache__/0002_alter_reviews_validate.cpython-39.pyc
codenerix_reviews/migrations/__pycache__/__init__.cpython-35.pyc
codenerix_reviews/migrations/__pycache__/__init__.cpython-39.pyc
django_codenerix_reviews-4.0.1.dist-info/LICENSE
django_codenerix_reviews-4.0.1.dist-info/METADATA
django_codenerix_reviews-4.0.1.dist-info/WHEEL
django_codenerix_reviews-4.0.1.dist-info/top_level.txt
django_codenerix_reviews-4.0.1.dist-info/RECORD
